pass_import/__about__.py
pass_import/__init__.py
pass_import/__main__.py
pass_import/audit.py
pass_import/auto.py
pass_import/clean.py
pass_import/core.py
pass_import/detecter.py
pass_import/errors.py
pass_import/manager.py
pass_import/tools.py
pass_import/decrypters/__init__.py
pass_import/decrypters/gpg.py
pass_import/formats/__init__.py
pass_import/formats/cli.py
pass_import/formats/csv.py
pass_import/formats/json.py
pass_import/formats/kdbx.py
pass_import/formats/otp.py
pass_import/formats/xml.py
pass_import/formats/yaml.py
pass_import/managers/__init__.py
pass_import/managers/aegis.py
pass_import/managers/andotp.py
pass_import/managers/applekeychain.py
pass_import/managers/bitwarden.py
pass_import/managers/blur.py
pass_import/managers/buttercup.py
pass_import/managers/chrome.py
pass_import/managers/clipperz.py
pass_import/managers/csv.py
pass_import/managers/dashlane.py
pass_import/managers/encryptr.py
pass_import/managers/enpass.py
pass_import/managers/figaropm.py
pass_import/managers/firefox.py
pass_import/managers/freeotp.py
pass_import/managers/gnomeauthenticator.py
pass_import/managers/gnomekeyring.py
pass_import/managers/gopass.py
pass_import/managers/gorilla.py
pass_import/managers/keepass.py
pass_import/managers/keepassx.py
pass_import/managers/keepassx2.py
pass_import/managers/keepassxc.py
pass_import/managers/keeper.py
pass_import/managers/lastpass.py
pass_import/managers/myki.py
pass_import/managers/networkmanager.py
pass_import/managers/nordpass.py
pass_import/managers/onepassword.py
pass_import/managers/padlock.py
pass_import/managers/passman.py
pass_import/managers/passpack.py
pass_import/managers/passpie.py
pass_import/managers/passwordstore.py
pass_import/managers/pwsafe.py
pass_import/managers/revelation.py
pass_import/managers/roboform.py
pass_import/managers/safeincloud.py
pass_import/managers/saferpass.py
pass_import/managers/sphinx.py
pass_import/managers/upm.py
pass_import/managers/zoho.py
usr/lib/password-store/extensions/import.bash
pass_import-3.5.dist-info/LICENSE
pass_import-3.5.dist-info/METADATA
pass_import-3.5.dist-info/WHEEL
pass_import-3.5.dist-info/entry_points.txt
pass_import-3.5.dist-info/top_level.txt
pass_import-3.5.dist-info/zip-safe
pass_import-3.5.dist-info/RECORD
