Metadata-Version: 2.1
Name: pass-import
Version: 3.5
Summary: A pass extension for importing data from most of the existing password manager.
Home-page: https://github.com/roddhjav/pass-import
Author: Alexandre Pujol
Author-email: alexandre@pujol.io
License: GPL3
Project-URL: Documentation, https://github.com/roddhjav/pass-import
Project-URL: Source, https://github.com/roddhjav/pass-import
Project-URL: Issues, https://github.com/roddhjav/pass-import/issues
Project-URL: Changelog, https://github.com/roddhjav/pass-import/blob/master/CHANGELOG.md
Keywords: password-store,password,pass,pass-extension,password-manager,importer
Classifier: Development Status :: 5 - Production/Stable
Classifier: Environment :: Console
Classifier: Intended Audience :: End Users/Desktop
Classifier: License :: OSI Approved :: GNU General Public License v3 or later (GPLv3+)
Classifier: Operating System :: MacOS :: MacOS X
Classifier: Operating System :: POSIX
Classifier: Operating System :: POSIX :: BSD
Classifier: Operating System :: POSIX :: Linux
Classifier: Operating System :: Microsoft :: Windows
Classifier: Programming Language :: Python
Classifier: Programming Language :: Python :: 3
Classifier: Programming Language :: Python :: 3 :: Only
Classifier: Programming Language :: Python :: 3.8
Classifier: Programming Language :: Python :: 3.9
Classifier: Programming Language :: Python :: 3.10
Classifier: Topic :: Security :: Cryptography
Requires-Python: >=3.7
License-File: LICENSE
Requires-Dist: pyaml
Requires-Dist: zxcvbn
Requires-Dist: requests
Provides-Extra: all
Requires-Dist: defusedxml ; extra == 'all'
Requires-Dist: pykeepass ; extra == 'all'
Requires-Dist: secretstorage ; extra == 'all'
Requires-Dist: cryptography ; extra == 'all'
Requires-Dist: file-magic ; extra == 'all'
Requires-Dist: jsonpath-ng ; extra == 'all'
Provides-Extra: decrypt
Requires-Dist: file-magic ; extra == 'decrypt'
Provides-Extra: encrypted_otp
Requires-Dist: cryptography ; extra == 'encrypted_otp'
Provides-Extra: filter
Requires-Dist: jsonpath-ng ; extra == 'filter'
Provides-Extra: gnomekeyring
Requires-Dist: secretstorage ; extra == 'gnomekeyring'
Provides-Extra: keepass
Requires-Dist: pykeepass ; extra == 'keepass'
Provides-Extra: xml
Requires-Dist: defusedxml ; extra == 'xml'
